{
	"Meta(Acqusition)": {
		"doc_id": "REPORT-news_r-02274",
		"doc_category": "REPORT",
		"doc_type": "news_r",
		"doc_name": "'우한 폐렴'에 온라인도 패닉.... 27일 하루에만 글 6만 5000건",
		"author": "정원엽",
		"publisher": "중앙일보",
		"publisher_year": "2020",
		"doc_origin": "중앙일보"
	},
	"Meta(Refine)": {
		"passage_id": "REPORT-news_r-02274-00001",
		"passage": "실검 2위에 올랐던 우한 폐렴이 1분 만에 삭제됐다.\n  (가짜)캐나다 생물학 연구소에서 중국인 연구원이 코로나 바이러스를 훔쳐 중국 우한시로 보냈다.\n  (가짜)인천에서 우한 폐렴 사망자가 나왔다 (가짜)  지난 설 연휴 기간 동안 각종 포털사이트와 페이스북, 유튜브 등에서 퍼진 거짓 정보들이다.\n  거짓뿐 아니라 미확인 정보와 추측도 난무하고 있다.\n  국내에서 신종 코로나 바이러스(우한 폐렴) 확진자가 4명으로 늘어나자 온라인 상에선 '우한 패닉'이 빠르게 확산되고 있다.\n    이런 현상은 실제 데이터로 확인된다.\n  민간 빅데이터분석 기관인 글로벌빅데이터연구소는 28일 '우한 폐렴'과 '신종 코로나 바이러스'가 언급된 정보량을 분석한 보고서를 냈다.\n  대상은 국내 뉴스·커뮤니티·블로그·카페·유튜브·트위터·인스타그램·페이스북·카카오스토리·지식인·기업/조직·정부/공공 등 12개 분야.\n  기간은 국내에서 첫 보도가 나온 지난해 12월 31일부터 설 연휴 마지막 날인 1월 27일까지였다.\n  첫 보도가 나온 12월 31일 언론 보도는 8건(한국언론진흥재단 뉴스 빅데이터 분석 시스템 빅카인즈 기준)으로 \"중국 우한서 원인불명의 폐렴 환자 27명이 발생했다\"는 내용이었다.\n  이날 각종 커뮤니티, 블로그 등 다른 채널에서 나온 정보량도 137건에 불과했다.\n  20일 이전까지만 해도 '우한 폐렴'은 주요 이슈에 끼지 못했다.\n  1월 1일부터 1월 19일까지 우한 폐렴 관련 보도는 597건(빅카인즈)으로 하루 평균 30여건 정도.\n  여타 채널의 정보량도 일평균 1000건 내외를 유지했다.\n   하지만 국내 첫 확진 환자가 나온 1월 20일 이후 온라인 정보량은 급증했다.\n  이날 하루 언론 보도는 223건으로 늘었고 채널 정보량은 8005건(뉴스 포함)까지 늘었다.\n  설 연휴동안 정보량은 8배나 뛰었다.\n  25일 3만 2792건, 26일 3만 8582건, 설 연휴 마지막 날인 27일 하루에만 6만 5112건을 기록했다.\n  연구소 측은 \"우한폐렴에 대한 공포가 온라인을 통해 빠른 속도로 확산되고 있다\"고 설명했다.\n  커뮤니티·블로그서 비공식 정보 퍼져 글로벌빅데이터연구소의 분석에 따르면 12월 31일 이후 지난 27일까지 채널별 정보량은 뉴스가 8만 6753건으로 가장 많았고 이어 커뮤니티(4만 9586건), 카페(3만 2093건), 트위터(2만 9841건), 블로그(2만 8953건), 네이버 지식인(5674건) 순이었다.\n ",
		"passage_Cnt": 1214
	},
	"Annotation": {
		"summary1": "국내에서 확진자가 늘어나 온라인 상에 우한 패닉이 확산되고 있으며 글로벌빅데이터연구소는 우한 폐렴과 신종 코로나 바이러스가 언급된 정보량을 분석한 보고서를 냈다.",
		"summary2": null,
		"summary3": "국내에서 신종 코로나 바이러스(우한 폐렴) 확진자가 4명으로 늘어나자 온라인 상에선 '우한 패닉'이 빠르게 확산되고 있다. 이런 현상은 실제 데이터로 확인된다. 민간 빅데이터분석 기관인 글로벌빅데이터연구소는 28일 '우한 폐렴'과 '신종 코로나 바이러스'가 언급된 정보량을 분석한 보고서를 냈다.",
		"summary_3_cnt": 167
	}
}