{
	"Meta(Acqusition)": {
		"doc_id": "REPORT-news_r-01727",
		"doc_category": "REPORT",
		"doc_type": "news_r",
		"doc_name": "‘신동빈의 롯데’ 굳히기…호텔롯데 상장이 최대 과제",
		"author": "김선영",
		"publisher": "중앙일보",
		"publisher_year": "2020",
		"doc_origin": "중앙일보"
	},
	"Meta(Refine)": {
		"passage_id": "REPORT-news_r-01727-00001",
		"passage": "신격호 롯데그룹 창업주이자 명예회장이 19일 세상을 떠나면서 롯데는 본격적인 ‘포스트 신격호’ 시대에 돌입했다.\n  재계는 이미 차남 신동빈(65) 롯데그룹 회장이 원톱 체제를 공고히 한 상태라 경영권의 큰 변화는 없을 것으로 보고 있다.\n  신동빈 회장은 지난해 2월 일본 롯데홀딩스 대표이사에 취임하고 6월 열린 롯데홀딩스 정기 주주총회에서 이사로 재선임되면서 한·일 롯데그룹 수장임을 분명히 했다.\n   신격호 유산 1조 … 지배구조에 영향 못 줘 상속과정에서 그룹의 지배구조가 달라질 가능성이 있을까.\n  신 명예회장 보유 재산은 최소 1조원을 웃돈다.\n  롯데지주(보통주 3.\n 10%, 우선주 14.\n 2%)·롯데쇼핑(0.\n 93%)·롯데제과(4.\n 48%)·롯데칠성음료(보통주 1.\n 30%, 우선주 14.\n 15%) 등 국내 4개 상장사 지분의 가치는 19일 종가 기준으로 2228억6000만원이다.\n  인천시 계양구에 시가 4500억원 상당의 골프장 부지(166만7392㎡)도 보유하고 있다.\n  비상장 주식인 롯데물산의 지분(6.\n 87%)도 예전 거래를 감안하면 1592억1000만원으로 추정된다.\n  호텔롯데의 최대주주인 일본 롯데홀딩스 지분(0.\n 45%)과 롯데그룹 전체 지배구조의 최정점에 있는 비상장기업 광윤사 지분(0.\n 83%)도 수천억원대로 추정된다.\n  신 명예회장은 유언장을 남기지 않았다.\n  상속인은 신영자 전 롯데복지재단 이사장과 신동주 전 롯데홀딩스 부회장, 신동빈 롯데그룹 회장, 신유미 롯데호텔 고문 등 4명이다.\n  재계에선 고인의 보유한 롯데홀딩스 지분이 많지 않고 상속세 부담을 고려하면 상속과정에서 그룹의 지배구조가 흔들릴 가능성은 별로 없다고 보고 있다.\n  유통 부문의 디지털 전환 부진, 화학 부문 경쟁력 유지 등 롯데그룹의 당면 현안도 신동빈 리더십 앞에 놓인 숙제다.\n  롯데그룹은 ▶유통 ▶석유화학·건설 ▶식·음료 ▶관광·서비스 등 4개의 축으로 움직인다.\n  지금의 롯데를 만든 핵심 부문은 유통이다.\n  오프라인에서 롯데백화점, 롯데마트, 롯데하이마트, 롯데아울렛, 편의점(세븐일레븐 등)에 더해 온라인의 롯데홈쇼핑, 롯데 e커머스 등의 인프라를 갖췄다.\n  신동빈 회장은 앞으로 덩치는 크고 노화한 조직을 개편하는 작업에 한층 더 속도를 낼 전망이다.\n  연초부터 롯데쇼핑 내부 인력재편을 진행하면서 유통 부문을 새로 만들다시피 하고 있다.\n  롯데그룹 내 무게 중심은 유통에서 석유화학으로 이동하고 있다.\n ",
		"passage_Cnt": 1221
	},
	"Annotation": {
		"summary1": "롯데그룹 신 명예회장이 세상을 떠났지만 경영권의 큰 변화는 없으며 신 회장이 조직 개편에 더욱 속도를 내면서 그룹의 무게 중심이 유통에서 석유화학으로 이동하고 있다.",
		"summary2": null,
		"summary3": "신격호 롯데그룹 창업주이자 명예회장이 19일 세상을 떠나면서 롯데는 본격적인 ‘포스트 신격호’ 시대에 돌입했다. 재계는 이미 차남 신동빈(65) 롯데그룹 회장이 원톱 체제를 공고히 한 상태라 경영권의 큰 변화는 없을 것으로 보고 있다. 신동빈 회장은 앞으로 덩치는 크고 노화한 조직을 개편하는 작업에 한층 더 속도를 낼 전망이다. 롯데그룹 내 무게 중심은 유통에서 석유화학으로 이동하고 있다.",
		"summary_3_cnt": 222
	}
}