{
	"Meta(Acqusition)": {
		"doc_id": "REPORT-news_r-16806",
		"doc_category": "REPORT",
		"doc_type": "news_r",
		"doc_name": "‘승자의 저주’ 피하려는 민주당…“그래도 통합당 기다린다”",
		"author": "심새롬",
		"publisher": "중앙일보",
		"publisher_year": "2020",
		"doc_origin": "중앙일보"
	},
	"Meta(Refine)": {
		"passage_id": "REPORT-news_r-16806-00001",
		"passage": " 33년만에 18개 상임위원장 자리를 독식한 더불어민주당이 30일 ‘승자의 저주’ 경계에 돌입했다.\n  단독 원구성 강행 후유증을 사전에 차단하려는 움직임이다.\n  김태년 원내대표는 이날 오전 원내대책회의에서 “일하는 국회 문은 항상 활짝 열려있다.\n  미래통합당에 말한다.\n  하루빨리 복귀하라”고 두 차례 언급했다.\n  하지만 이날 통합당에서 나온 “3차 추경 처리 1주일 연기” 주장은 거부했다.\n  통합당 향한 역공제1야당 없이 반쪽 국회를 개문발차한 여당의 우려는 ‘민주당=의회 독재’란 여론이다.\n  당장 공격 상대(통합당)를 지목해 역공하는 발언이 나왔다.\n  박홍근 의원은 이날 페이스북에 “통합당이 ‘민주당을 독선과 오만의 의회 독재세력으로 최대한 낙인을 찍고 프레임에 가둠으로써 다음 대선에 유리한 여론지형을 만들겠다’는 저급한 속내를 드러냈다”고 썼다.\n  전날 통합당에서 “헌정 사상 초유의 여당 폭주”(최형두 원내대변인), “대한민국 의회 치욕의 날”(김은혜 대변인)이라고 반발한 걸 ‘대선용 여론전’으로 규정한 거다.\n  민주당 지도부는 원구성 합의 실패의 책임을 통합당으로 돌렸다.\n  김영진 민주당 원내수석부대표는 이날 라디오 인터뷰에서 “김종인 (통합당) 비대위원장이 18대0으로 해서 여당이 다 가져가라, 원만한 원 구성을 만들기보다는 차기 대선 전략으로 민주당이 18개를 다 해서 한번 책임져봐라, 2년 후 우리가 대선에서 이긴다, 이런 전략적 목표를 갖고 접근했다”고 주장했다.\n  투항 기다리지만…민주당은 한편에선 ‘통합당 기다리기’ 전략을 세우고 있다.\n  김태년 원내대표는 이날 중앙일보와의 통화에서 “(통합당이) 이렇게 나가버리고 나중에 들어오려면 멋쩍을 수 있다.\n  언젠간 들어올 것”이라고 했다.\n  박성준 대변인은 기자들과 만나 “(3차) 추경 처리 전까지는 (여야) 냉각기가 될 것”이라며 “야당이 7,8월 여론전을 펴다 8월 말 (내년도) 예산안 처리, 9월 정기국회 때는 들어오지 않겠나”라고 말했다.\n  민주당 핵심 관계자도 “국회는 원래 야당의 장이다.\n  (통합당은) 언제든 국회로 들어와 싸우겠다는 명분을 가질 수 있다”고 내다봤다.\n  하지만 상황이 민주당 바람대로 흘러갈지는 미지수다.\n  이미 18대0으로 다 내준  김종인 비대위 체제가 대여 강경 노선을 예상보다 오래 유지할 가능성이 작지 않다.\n  김 위원장은 전날 통합당 의원총회에서 “우리가 지금은 상당히 괴로움을 느끼는 순간이 될지 모르지만, 장차 우리가 달성하고자 하는 목표를 위해서 오히려 하나의 큰 약이 될 수 있다”고 했다.\n ",
		"passage_Cnt": 1266
	},
	"Annotation": {
		"summary1": "민주당 지도부는 원구성 합의 실패 책임을 통합당으로 돌렸고 김 민주당 원내수석부대표는 라디오 인터뷰에서 김 비대위원장이 전략적 목표를 갖고 접근했다고 말했다.",
		"summary2": null,
		"summary3": "김영진 민주당 원내수석부대표는 이날 라디오 인터뷰에서 “김종인 (통합당) 비대위원장이 18대0으로 해서 여당이 다 가져가라, 원만한 원 구성을 만들기보다는 차기 대선 전략으로 민주당이 18개를 다 해서 한번 책임져봐라, 2년 후 우리가 대선에서 이긴다, 이런 전략적 목표를 갖고 접근했다”고 주장했다. 민주당 지도부는 원구성 합의 실패의 책임을 통합당으로 돌렸다.",
		"summary_3_cnt": 204
	}
}