{
	"Meta(Acqusition)": {
		"doc_id": "REPORT-news_r-11090",
		"doc_category": "REPORT",
		"doc_type": "news_r",
		"doc_name": "[김민석의 Mr. 밀리터리] ‘민주국가 북한’ 기대에 도발 우려 섞인 김정은 유고설",
		"author": "김선영",
		"publisher": "중앙일보",
		"publisher_year": "2020",
		"doc_origin": "중앙일보"
	},
	"Meta(Refine)": {
		"passage_id": "REPORT-news_r-11090-00001",
		"passage": "북한의 권력 이동독재자의 종말은 비참했다.\n  히틀러는 1945년 4월 30일 소련군이 독일 베를린에 진입하자 지하벙커에서 “내 시신을 완전히 불태우라”는 유서를 남기고 목숨을 끊었다.\n  이탈리아 독재자 무솔리니는 로마를 탈출했지만, 시민에게 잡혀 처형당했다.\n  2011년 ‘아랍의 봄’ 혁명으로 튀니지·이집트·리비아의 독재자가 물러났다.\n  절대권력자들은 시민의 시위에 힘없이 무너졌다.\n  지난해에도 알제리와 수단의 독재자가 시민의 저항에 퇴진했다.\n  아산정책연구원 장지향 중동센터장은 “폭압 정치와 부패, 빈곤은 독재정권의 약점이지만 몰락의 결정적 이유는 아니다”라며 “독재정권은 매우 우발적인 사건으로 여론 장악력을 잃는 순간 위기는 시작된다”고 했다.\n  그러나 독재정권의 붕괴는 내전과 수많은 난민도 속출했다.\n  장 센터장이 말하는 ‘우발적 사건’이 독재국가 북한에서도 일어날까.\n  최근 김정은 북한 국무위원장의 유고설이다.\n  그런데 김 위원장의 유고설을 바라보는 정부와 언론의 시각은 판이하다.\n  김 위원장이 ‘심혈관 수술을 잘못해 뇌사상태에 빠졌다’와 ‘순시 중에 쓰러져 사망했다’에서부터 ‘건재하다’까지다.\n  그의 전용열차가 원산에 장기간 정차해 있고, 동생인 김여정 노동당 부부장과 최룡해 최고인민회의 상임위원장 등 북한 지도부가 언론에서 사라졌다.\n  김연철 통일부 장관은 “북한에 특이 동향이 없다”고 지난 28일 밝혔다.\n  문정인 대통령통일외교안보특보도 “(김 위원장이) 건재하다”고 했다.\n  군 정보당국도 어제 김 위원장이 “정상적으로 국정운영을 하고 있다”는 입장이다.\n  이에 대해 다수의 정보 관계자는 김정은에 관한 정보가 없다고 한다.\n  외신도 엇갈린다.\n  워싱턴 포스트(WP)는 “김정은 사망설에 북한이 뒤숭숭하고, 사재기가 극성”이라고 보도했다.\n  러시아 타스통신은 “평양 주민들이 평소와 같고, 대동강변에선 노래가 흘러나왔다”며 WP와 정반대 기사를 냈다.\n  트럼프 미 대통령은 그제 백악관 기자회견에서 “지금은 그(김정은)가 건강하기만 바란다.\n  괜찮기를 바란다”고 말했다.\n  트럼프 대통령의 뉘앙스는 약간 다르다.\n  그의 “괜찮길 바란다”는 김정은 건강에 문제가 있다는 의미로도 들린다.\n  다급해진 중국은 지난 25일 김 위원장에게 조언을 명분으로 의료진 등 대표단을 북한에 파견했다고 한다.\n  북한 정탐이 목적인 것 같다.\n  종합하면 김 위원장과의 이해관계에 따라 그의 유고설에 대한 판단이 다르다.\n ",
		"passage_Cnt": 1221
	},
	"Annotation": {
		"summary1": "김 위원장의 유고설을 보는 시각이 판이한 가운데 중국은 다급하게 북한을 정탐할 목적으로 북한에 대표단을 파견하였다.",
		"summary2": null,
		"summary3": "다급해진 중국은 지난 25일 김 위원장에게 조언을 명분으로 의료진 등 대표단을 북한에 파견했다고 한다. 북한 정탐이 목적인 것 같다. 김연철 통일부 장관은 “북한에 특이 동향이 없다”고 지난 28일 밝혔다. 최근 김정은 북한 국무위원장의 유고설이다. 김 위원장이 ‘심혈관 수술을 잘못해 뇌사상태에 빠졌다’와 ‘순시 중에 쓰러져 사망했다’에서부터 ‘건재하다’까지다. 그런데 김 위원장의 유고설을 바라보는 정부와 언론의 시각은 판이하다.",
		"summary_3_cnt": 247
	}
}