{
	"Meta(Acqusition)": {
		"doc_id": "REPORT-news_r-12083",
		"doc_category": "REPORT",
		"doc_type": "news_r",
		"doc_name": "역사 속 사라지는 더불어시민당…與 '꼼수' 위성정당 60일史",
		"author": "하준호",
		"publisher": "중앙일보",
		"publisher_year": "2020",
		"doc_origin": "중앙일보"
	},
	"Meta(Refine)": {
		"passage_id": "REPORT-news_r-12083-00002",
		"passage": " 민주당 선택을 받지 못한 정개련은 “민주당이 플랫폼 정당 간 통합을 요구해 놓고 갑자기 일방 통보했다”며 반발했다.\n  민주당 핵심 관계자는 “정개련에 참여키로 했었던 녹색당이 성소수자 후보를 내세워 선거 쟁점으로 떠오를 수 있는 점, ‘이석기 석방’을 주장하는 민중당과 연합할 경우 ‘종북 프레임’에 휘말릴 수 있는 점 등을 종합적으로 고려했다”고 회고했다.\n  정개련은 3월 26일 해산했다.\n  그 사이 시민당은 3월 18~22일 공천 신청·심사를 진행해 5일 만에 비례 후보 34명을 추려 발표했다.\n  민주당 비례대표 후보들은 3월 20일 정당법 위반(탈당 강요) 논란 속에서도 시민당으로 건너갔고, 11번 이후 순번에 배치됐다.\n  시민당의 “우리는 빈 그릇”이란 공언과 달리 1~10번에 자체 후보를 추천하면서 민주당 비례 후보들이 공식 우려를 표명하기도 했다.\n  민주당·시민당은 공식 선거운동 기간(4월 2~14일) 합동 선거대책위원회의·공약발표 등을 이어가며 ‘한 몸 마케팅’을 폈다.\n  그러다 중앙선관위가 ‘쌍둥이 유세차’ 운행에 제동을 거는 등 선거법을 줄 타다 미끄러지는 일도 있었다.\n  ④180석 거여(巨與) 탄생과 남은 논란=민주당이 앞순위 기호를 위해 현역 의원을 꿔주는 등 한 몸처럼 움직인 두 당은 총선 이후 180석 거대 여당이 됐다.\n  총선 결과 민주당이 지역구 163석을, 시민당이 비례대표 17석을 확보하면서다.\n  양정숙(15번) 당선인이 부동산 의혹으로 제명된 데 이어 소수정당 몫으로 합류했던 용혜인(5번·기본소득당), 조정훈(6번·시대전환) 당선인이 12일 시민당 최고위에서 제명되고 원 소속 정당으로 복귀하면서 거여의 의석수는 177석으로 확정됐다.\n  다만, 여당의 한발 늦은 ‘꼼수’가 초래한 ‘졸속 공천’ 논란은 현재진행형이다.\n  부동산실명제 위반, 명의신탁 의혹이 불거져 지난 7일 제명된 양정숙 당선인은 후보검증 과정에서 허위진술한 정황이 드러나면서 정당이 자당 당선인을 검찰에 고발하는 촌극이 벌어졌다.\n  시민당 자체 후보인 윤미향(7번) 당선인도 정의기억연대(옛 한국정신대문제대책협의회) 이사장 시절 기부금 유용 의혹 등으로 최근 논란의 중심에 섰다.\n  민주당은 미래한국당이 ‘준연동형 비례제 폐지 논의’를 조건으로 제의한 ‘2+2 회담’에는 응하지 않으면서도 통합당·한국당을 향해 “하나의 먹이를 두고 쌍두뱀처럼 상임위와 국고보조금을 두고 싸우고 있다”(12일 이해찬 대표)며 합당을 압박하고 있다.\n ",
		"passage_Cnt": 1219
	},
	"Annotation": {
		"summary1": "한 몸처럼 움직인 민주당·시민당은 총선 이후 당선인 제명과 원 소속 정당으로 복귀 등으로 177석 의석수로 확정됐다.",
		"summary2": null,
		"summary3": "양정숙(15번) 당선인이 부동산 의혹으로 제명된 데 이어 소수정당 몫으로 합류했던 용혜인(5번·기본소득당), 조정훈(6번·시대전환) 당선인이 12일 시민당 최고위에서 제명되고 원 소속 정당으로 복귀하면서 거여의 의석수는 177석으로 확정됐다. 민주당이 앞순위 기호를 위해 현역 의원을 꿔주는 등 한 몸처럼 움직인 두 당은 총선 이후 180석 거대 여당이 됐다. 민주당·시민당은 공식 선거운동 기간(4월 2~14일) 합동 선거대책위원회의·공약발표 등을 이어가며 ‘한 몸 마케팅’을 폈다.",
		"summary_3_cnt": 273
	}
}