{
	"Meta(Acqusition)": {
		"doc_id": "REPORT-news_r-12788",
		"doc_category": "REPORT",
		"doc_type": "news_r",
		"doc_name": "“경희사이버대 온라인 직무강의 통해 생활지원사 능률 높인다”",
		"author": "안희",
		"publisher": "중앙일보",
		"publisher_year": "2020",
		"doc_origin": "중앙일보"
	},
	"Meta(Refine)": {
		"passage_id": "REPORT-news_r-12788-00001",
		"passage": "경희사이버대학교는 코로나 19 확산 방지하기 위해 독거노인종합지원센터(보건복지부 위탁)와 함께 노인맞춤돌봄서비스 온라인 직무교육 기초과정 강의 제작과 송출을 진행하고 있다.\n    제작된 직무강의는 경희사이버대 사회교육원 LMS를 통해 노인맞춤돌봄서비스 수행기관 663 개소(광역지원기관 16개소 및 수행기관 647개소)에 종사하는 전담사회복지사 약 1,300여명과 생활지원사 약18,700명에게 송출되고 있다.\n  수강생의 만족도도 높고 교육의 효율성도 확인되었기에 경희사이버대학교와 독거노인종합지원센터는 노인맞출돌봄서비스 심화과정 또한 제작을 완료했다.\n    성동구 마장동에 위치한 성동노인종합복지관에서 생활지원사로 근무하고 있는 윤부순 씨는 “오랫동안 생활지원사를 하면서 많은 교육을 받아왔었다.\n  단체로 진행되는 교육에 있어 워낙 인원이 많다보니 오프라인 교육에서 집중하기가 힘들었다.\n  하지만 온라인 직무강의는 1:1 수업이라고 생각될 정도로 집중이 잘됐다”고 소감을 전하며, 강의를 들으면서 놓친 부분이 있으면 다시 볼 수 있어 자세하게 배울 수 있었다고 말했다.\n  앞서 경희사이버대학교는 문화세계의 창조라는 설림이념 아래 대학의 사회적 책무를 다하기 위해 ‘Engagement21’ 프로그램 운영을 통해 취약 계층에게 대학교육 기회의 문턱을 낮추고 고등교육을 사회에 제공하고 있다.\n  한편, 경희사이버대학교는 오는 6월 1일(월) 부터 7월 10일(금)까지 2020학년도 2학기 신·편입생을 모집한다.\n    이번 모집학과(전공)는 미래·문화·글로벌리더십계열 소프트웨어디자인융합스쿨(컴퓨터정보통신공학전공, AI사이버보안전공, ICT융합콘텐츠전공, 산업디자인전공, 시각미디어디자인전공), 미래인간과학스쿨(재난방재과학전공, 공공안전관리전공), 보건의료관리학과, 한방건강관리학과, 후마니타스학과, NGO사회혁신학과, 상담심리학과, 사회복지학부(사회복지전공, 노인복지전공, 아동·보육전공), 미디어문예창작학과, 스포츠경영학과, 실용음악학과, 일본학과, 중국학과, 미국문화영어학과, 한국어문화학과, 한국어학과, 문화커뮤니케이션학부(미디어영상홍보전공, 문화예술경영전공), 마케팅·지속경영리더십학과, 글로벌경영학과, 세무회계학과, 금융부동산학부(금융경제전공, 도시계획부동산전공), 호텔·레스토랑경영학과, 관광레저항공경영학부(관광레저경영전공, 항공·공항서비스경영전공), 외식조리경영학과이다.\n  수능·내신 성적과 관계없이 자기소개(80%)와 인성검사(20%)로 선발하며, 고등학교 졸업 이상의 학력을 가진 사람 또는 동등 학력이인정되는 자라면 누구나 지원할 수 있다.\n ",
		"passage_Cnt": 1275
	},
	"Annotation": {
		"summary1": "경희사이버대학교는 사회교육원 LMS를 통해 노인맞춤돌봄서비스 온라인 직무교육 기초과정 강의를 송출하고 있다.",
		"summary2": "경희사이버대학교는 코로나 19 확산 방지하기 위해 독거노인종합지원센터(보건복지부 위탁)와 함께 노인맞춤돌봄서비스 온라인 직무교육 기초과정 강의 제작과 송출을 진행하고 있다. 제작된 직무강의는 경희사이버대 사회교육원 LMS를 통해 노인맞춤돌봄서비스 수행기관 663 개소(광역지원기관 16개소 및 수행기관 647개소)에 종사하는 전담사회복지사 약 1,300여명과 생활지원사 약18,700명에게 송출되고 있다.",
		"summary3": null,
		"summary_3_cnt": null
	}
}