{
	"Meta(Acqusition)": {
		"doc_id": "REPORT-news_r-28709",
		"doc_category": "REPORT",
		"doc_type": "news_r",
		"doc_name": "'칼' 잡은 바이든, 트럼프표 정책 싹 갈아엎는다…거리두기 강화, 감세 철회 이어질 듯 ",
		"author": "백희연",
		"publisher": "중앙일보",
		"publisher_year": "2020",
		"doc_origin": "중앙일보"
	},
	"Meta(Refine)": {
		"passage_id": "REPORT-news_r-28709-00001",
		"passage": "조 바이든 미국 대통령 당선인이 내년 1월 20일 ‘바이든 행정부’ 출범을 위한 본격적인 준비에 들어갔다.\n  정권 인수 절차에 속도를 내며 선거 결과에 불복하는 도널드 트럼프 대통령을 압박하는 모양새다.\n    바이든 당선인은 인수위원회 웹사이트인 ‘빌드백베터닷컴(BuildBackBetter.\n com)’을 지난 4일(현지시간) 개설했다.\n  경제정책 ‘바이드노믹스’의 핵심 구호인 ‘더 나은 재건’에서 홈페이지 주소를 따왔다.\n  바이든 당선인이 미국의 최우선 과제로 제시한 4가지는 신종 코로나바이러스 감염증(코로나19)·경제 회복·인종 문제·기후변화다.\n  이 4가지 분야에서 바이든 행정부는 트럼프 행정부와 선명한 차별화에 나설 예정이다.\n  기조는 트럼프 정책 뒤집기, 이른바 'ABT(Anything But Trump)' 다.\n   가장 시급한 현안, 코로나19바이든 당선인은 지난 7일(현지시간) 승리 선언 연설에서 자신의 최우선 과제로 코로나19를 꼽았다.\n  트럼프 정부의 코로나19 대응 실패를 집중 공격해 승리를 거머쥔 만큼 바이든 당선인은 코로나19 확산 차단에 사활을 걸 것으로 보인다.\n  인수위 웹사이트에 따르면 바이든 당선인은 7개의 핵심 계획을 세워 코로나를 물리치겠다고 밝혔다.\n  ^과학에 귀를 기울이고 ^공중보건과 관련한 결정은 전문가와 상의하며^신뢰와 투명성, 책임을 강화하겠다는 것이다.\n  이런 원칙을 토대로 바이든 당선인은 미국 질병관리센터(CDC)에 코로나19 방역관련 세부지침을 마련하라고 지시할 예정이다.\n  유행 정도에 따른 사회적 거리 두기 강도 등 단계별·지역별 행동지침 마련이 핵심이다.\n    트럼프 행정부는 그간 코로나19 대유행 상황에도 경제 재개를 위해 각종 봉쇄조치를 조기에 해제했다.\n  또 고위 공직자들이 공공장소에서 마스크를 쓰지 않는 등 코로나19의 심각성을 의도적으로 평가절하한다는 비판을 받았다.\n  바이든 당선인은 이와 정반대로 취임과 동시에 마스크 의무착용, 코로나 검사 확대, 치료제 및 백신 무료 제공 등 적극적 방역 정책을 내세울 예정이다.\n   9일(현지시각)엔 코로나19 대응 태스크포스(TF)팀도 공식 출범한다.\n  공동 팀장은 비멕 머시 전 공중보건서비스단장과 데이비드 케슬러 전 식품의약국(FDA) 국장이 맡을 것으로 전해졌다.\n  코로나19 상황이 안정되면 트럼프 행정부가 폐기를 시도한 ‘건강보험개혁법(오바마 케어)’도 복구시킬 것으로 관측된다.\n ",
		"passage_Cnt": 1203
	},
	"Annotation": {
		"summary1": "트럼프 정부의 코로나19 대응 실패를 공략하며 승리를 얻은 바이든 당선인이 선거 결과에 불복하는 트럼프를 압박하기 위해 바이든 행정부를 출범 시켰다.",
		"summary2": "조 바이든 미국 대통령 당선인이 내년 1월 20일 ‘바이든 행정부’ 출범을 위한 본격적인 준비에 들어갔다. 정권 인수 절차에 속도를 내며 선거 결과에 불복하는 도널드 트럼프 대통령을 압박하는 모양새다. 트럼프 정부의 코로나19 대응 실패를 집중 공격해 승리를 거머쥔 만큼 바이든 당선인은 코로나19 확산 차단에 사활을 걸 것으로 보인다.",
		"summary3": null,
		"summary_3_cnt": null
	}
}