{
	"Meta(Acqusition)": {
		"doc_id": "REPORT-news_r-16684",
		"doc_category": "REPORT",
		"doc_type": "news_r",
		"doc_name": "다시 서울로 몰리는 사람들…올해 수도권 인구, 비수도권 추월",
		"author": "하남현",
		"publisher": "중앙일보",
		"publisher_year": "2020",
		"doc_origin": "중앙일보"
	},
	"Meta(Refine)": {
		"passage_id": "REPORT-news_r-16684-00001",
		"passage": "사람들이 다시 서울 부근으로 모여들고 있다.\n  수도권 순 유입 인구 규모가 점점 커지고 있다.\n  지방에서 수도권으로 옮긴 인구가 수도권에서 빠져나간 인구보다 많다는 의미다.\n  올해 수도권 인구는 비수도권 인구를 처음으로 추월할 전망이다.\n  지방에 양질의 일자리와 함께 삶의 질을 높일 수 있는 문화 여건이 갖춰지지 않으면 수도권 쏠림 현상은 심화할 거라는 진단이 나온다.\n  지난해 수도권 순 유입 8만3000명 통계청이 29일 내놓은 ‘최근 20년간 수도권 인구 이동과 향후 인구전망’에 따르면 지난해 수도권 순 유입 인구는 8만3000명이다.\n  수도권 전입 인구수 (47만6000명)가 전출(39만3000명)보다 이만큼 많다는 뜻이다.\n   수도권에선 지난 2011년(-8000명) 처음으로 전출 인구가 전입 인구를 넘어섰다.\n  이후 등락을 반복하다가 2017년 이후 지난해까지 3년 연속 수도권 인구가 늘었다.\n  수도권 안에선 서울의 순 유입 인구가 가장 많았다.\n  지난해 4만6000명을 기록했다.\n  경기는 3만5000명, 인천은 2000명이다.\n  수도권 내에선 서울에서 경기도로 나가는 인구가 많았다.\n  지난해 9만6000명이 서울에서 경기도로 옮겼다.\n  최근 20년간 10대와 20대는 지속해서 수도권으로 들어왔다.\n  지난해의 경우 10대는 9000명, 20대는 7만6000명 순 유입을 기록했다.\n  반면 40대 이상은 2008년 이후 계속해서 수도권을 빠져나갔다.\n  지난해 40대 이상은 수도권 전출 인구가 전입 인구보다 1만2000명 많았다.\n    수도권으로 다시 인구가 몰리는 건 일자리 때문이다.\n  지난해 수도권 순 유입 인구 중 6만4000명은 직업 때문이다.\n  교육(2만1000명), 주택(1만2000명)이 뒤를 이었다.\n  수도권 순 유출 이유는 자연환경(-1만1000명), 가족(-8000명) 때문이었다.\n     김진 통계청 인구동향과장은 “정부 청사 및 공공기관의 지방 이전이 2017년까지 거의 마무리되면서 서울에서 지방으로 거주지를 옮긴 공공기관 및 연관 직종 종사자 수가 줄어든 게 수도권 순 유입을 다시 증가시키는 요인이 됐다”고 설명했다.\n     부산‧경남‧대구‧경북‧광주 5개 시도 인구는 최근 20년간 계속해서 수도권으로 순 유입 했다.\n  그 규모는 2015년까지 지속해서 감소하다 최근 증가 추세로 돌아섰다.\n  지난해 수도권으로 순 유입한 인구가 가장 많은 곳은 부산(1만4000명)이다.\n ",
		"passage_Cnt": 1216
	},
	"Annotation": {
		"summary1": "수도권 순 유입 인구 규모가 커지면서 수도권 쏠림 현상이 심화할 거라는 진단이 나오는 것은 일자리 때문에 인구가 다시 수도권으로 몰려서이다.",
		"summary2": "수도권 순 유입 인구 규모가 점점 커지고 있다. 지방에 양질의 일자리와 함께 삶의 질을 높일 수 있는 문화 여건이 갖춰지지 않으면 수도권 쏠림 현상은 심화할 거라는 진단이 나온다. 수도권으로 다시 인구가 몰리는 건 일자리 때문이다.",
		"summary3": null,
		"summary_3_cnt": null
	}
}