{
	"Meta(Acqusition)": {
		"doc_id": "REPORT-news_r-08153",
		"doc_category": "REPORT",
		"doc_type": "news_r",
		"doc_name": "1조6000억 피해 라임 그놈들 잡혀간다···정관계 로비장부설까지",
		"author": "이후연",
		"publisher": "중앙일보",
		"publisher_year": "2020",
		"doc_origin": "중앙일보"
	},
	"Meta(Refine)": {
		"passage_id": "REPORT-news_r-08153-00001",
		"passage": "현재까지 1조6000억원의 피해액을 낸 라임자산운용 환매 중단 사태에 대한 검찰 수사가 최근 ‘급진전’됐다.\n 사건을 수사 중인 서울남부지검 형사6부(부장 조상원)는 최근 라임 펀드를 만들고 부실을 알면서도 판매를 해 온 신한금융투자 전 본부장 임모씨와 이종필 라임 전 부사장의 도피를 도운 조력자 강모씨, 한모씨를 구속했다.\n  또 ‘회장님’으로 알려진 김모씨가 실소유해온 스타모빌리티를 압수수색했다.\n  ‘회장님’김씨의 측근으로 알려진 김모 전 스타모빌리티 사내이사는 별건을 수사 중이던 경찰에 체포됐다.\n  라임 사태에 연루된 주요 인물들이 속속 검·경이 친 그물망에 걸려들고 있다.\n 검찰은 구속한 사람들은 물론, 현재 소재를 파악하고 있는 라임 사태의 주요 인물들을 계속 불러 조사할 것으로 보인다.\n  대표적인 인물은 1조원이 넘는 라임 투자금을 모은 대신증권 전 센터장 장모씨다.\n  공개된 한 라임 투자 피해자와의 녹취록에서 장씨는 라임을 정상화시킬 인물로 김 전 스타모빌리티 회장을 ‘회장님’으로 칭하며 “어마어마하게 로비를 하는 사람” “재향군인회상조회도 인수할 것”이라고 밝혔다.\n  또 전 청와대 행정관 김모씨의 명함을 피해자에게 보여주며 “이 사람이 핵심 키”라고 언급하기도 했다.\n 장씨는 김 전 회장에게 자기도 이용당했다고 주장하고 있지만 이종필 전 부사장과 김 전 회장, 전 청와대 행정관 김씨와 모두 알고 지냈던 만큼, 검찰은 조만간 장씨를 소환해 조사할 방침인 것으로 알려졌다.\n  전직 청와대 행정관인 김씨에 대한 조사도 불가피한 상황이다.\n  김씨는 ‘회장님’ 김씨로부터스타모빌리티 전신인 인터불스의 법인카드를 받아 강남 유흥주점 등에서 사용한 것으로 알려졌다.\n  또 김씨의 동생은 스타모빌리티의 사외이사로 근무하며 급여 명목으로 매월 300만원 가량을 받아왔던 것으로 나타났다.\n 장씨와 김씨 외에도 검찰은 피의자나 참고인 자격으로 라임·스타모빌리티·수원여객 등 라임 사태와 연관된 기업들의 직원들도 소환해 조사할 방침이다.\n 검찰 관계자는 “관련 인물들에 대한 수사는 물론 기업들의 압수수색도 불가피할 것”이라고 전망했다.\n  이미 대신증권·우리은행·신한금융투자 등을 압수수색한 검찰은 라임과 관련된 자산운용사도 함께 압수수색했다고 밝혔다.\n  또 일부 라임 소속 직원들의 휴대전화를 압수수색해 포렌식 작업에 나선 상황이다.\n 김 전 수원여객 전무 등 도주한 라임 사태의 주역들을 검거하는 데 주력한다는 방침이다.\n ",
		"passage_Cnt": 1208
	},
	"Annotation": {
		"summary1": "검찰이 라임자산운용 환매 중단과 관련된 주역들의 검거와 자산운용사의 수사에 매진하고 있다.",
		"summary2": "김 전 수원여객 전무 등 도주한 라임 사태의 주역들을 검거하는 데 주력한다는 방침이다. 현재까지 1조6000억원의 피해액을 낸 라임자산운용 환매 중단 사태에 대한 검찰 수사가 최근 ‘급진전’됐다. 이미 대신증권·우리은행·신한금융투자 등을 압수수색한 검찰은 라임과 관련된 자산운용사도 함께 압수수색했다고 밝혔다.",
		"summary3": null,
		"summary_3_cnt": null
	}
}