{
	"Meta(Acqusition)": {
		"doc_id": "REPORT-news_r-08449",
		"doc_category": "REPORT",
		"doc_type": "news_r",
		"doc_name": "\"교도소 무상급식\"\"인천 촌구석\"···선거 다가오자 또 도진 막말",
		"author": "현일훈",
		"publisher": "중앙일보",
		"publisher_year": "2020",
		"doc_origin": "중앙일보"
	},
	"Meta(Refine)": {
		"passage_id": "REPORT-news_r-08449-00001",
		"passage": "4·15 총선 공식 선거운동이 2일부터 시작된다.\n  전문가들은 막말과 후보 단일화, 신종 코로나바이러스 감염증(코로나19), 비례 정당 등장을  이번 선거의 승패를 판가름할 4대 변수로 꼽았다.\n   ①막말=미래통합당은 1일 문재인 대통령을 향한 '교도소 무상급식' 발언을 공식 사과했다.\n  당 유튜브 채널 진행자인 박창훈씨는 전날 문 대통령을 겨냥해 “임기 끝나고 나면 교도소에서 친환경 무상급식을 먹이면 된다”고 비아냥댔다가 막말 논란에 휩싸였다.\n  청와대는 “입장이 없다”면서도 “그 영상이 막말인지, 대선 불복 심리가 깔린 것인지는 국민이 판단할 것”이라고 말했다.\n   후폭풍이 거세자 박형준 공동 선거대책위원장은 당 선거대책회의에서 “선대위원장으로서 유감과 사과의 말씀을 전한다”며 “정권과 여당 잘못은 엄중히 비판하되 정도와 품격을 지켜 달라”고 말했다.\n  박 위원장 외에도 “지각없는 사람이 쓸데없는 소리를 했다”(김종인), “막말로 여론을 얻을 수 있는 시대는 지났다”(유승민) 등 당 주요 인사들의 진화성 발언이 종일 이어졌다.\n  전날엔 인천 연수갑 정승연(통합당) 후보가 선거사무실을 방문한 유승민 의원에게 “인천 촌구석까지 와주셔서 감사하다”고 했다가 ‘지역 비하’ 논란이 일자 “진심으로 사과드린다”며 입장문을 낸 일도 있었다.\n  박상철 경기대 교수는 “지금 같은 시기엔 막말 한 마디가 판세를 큰 영향을 줄 수 있다”고 말했다.\n  막말이 선거판을 뒤흔든 경우가 꽤 있다.\n  2004년 17대 총선에서 당시 정동영 열린우리당 의장이 “60·70대는 투표 안 해도 괜찮다”고 말했다가 곤욕을 치른 건 선거 때마다회자된다.\n  2012년 19대 총선 때는 당시 민주통합당 김용민 후보가 과거(2004년) 인터넷 라디오에서 “유영철을 풀어 라이스(전 미 국무장관)를 강간해 죽이는 거예요” 등의 막말을 한 게 뒤늦게 알려져 민주당에 큰 악재가 됐다.\n   ②후보 단일화=선거 때마다 등장한 단일화 변수는 이번 선거라고 예외가 아니다.\n  여권에선 주로 민주당과 정의당 간에, 야권에선 통합당과 통합당 이탈 무소속 후보 간에 단일화가 거론된다.\n  그간 정의당을 비롯한 각 정당은 자강론을 주장해왔다.\n  하지만 선거일이 다가올수록 일대일 구도를 만들어 당선 가능성을 높여야 한다는 현실적인 문제에 직면하게 되면서, 단일화를 검토하거나 추진 중이다.\n  심상정 정의당 대표는 이날 라디오에서 여영국 후보의 경남 창원 성산과 이정미 후보가 출마한 인천 연수을의 후보 단일화 가능성에 대해 “지역 논의를 지켜볼 것”이라고 말했다.\n ",
		"passage_Cnt": 1265
	},
	"Annotation": {
		"summary1": "전문가들은 4·15 총선에 대해 막말과 후보 단일화 등의 4가지 변수로 인해 승패가 날 것이라고 밝혔다.",
		"summary2": "4·15 총선 공식 선거운동이 2일부터 시작된다. 전문가들은 막말과 후보 단일화, 신종 코로나바이러스 감염증(코로나19), 비례 정당 등장을 이번 선거의 승패를 판가름할 4대 변수로 꼽았다.",
		"summary3": null,
		"summary_3_cnt": null
	}
}