{
	"Meta(Acqusition)": {
		"doc_id": "REPORT-news_r-15393",
		"doc_category": "REPORT",
		"doc_type": "news_r",
		"doc_name": "트럼프 \"방위비 낼 때까지 미군 감축…독일 얘기만 아니다\"",
		"author": "정효식",
		"publisher": "중앙일보",
		"publisher_year": "2020",
		"doc_origin": "중앙일보"
	},
	"Meta(Refine)": {
		"passage_id": "REPORT-news_r-15393-00001",
		"passage": " 도널드 트럼프 미국 대통령이 15일(현지시간) \"독일이 국내총생산(GDP)의 2% 방위비를 낼 때까지 미군을 절반 규모로 감축할 것\"이라고 밝혔다.\n  주독 미군 규모를 최대 5만2000명에서 2만5000명으로 줄이겠다고 하면서다.\n  이날 트럼프 대통령이 \"독일 얘기만이 아니다\"라고 한 데 대해 미 고위 관리는 이날 \"대통령은 한국 등 다른 동맹도 방위비를 더 부담해야 한다는 분명한 입장\"이라고 압박했다.\n  트럼프 대통령은 이날 백악관에서 공화당도 주독미군 철수를 반대하는 데 재검토하느냐는 기자들의 질문에 5분여 동안 독일의 방위비 체납과 러시아와의 가스관 사업, 대미 무역 문제까지 거론하며 전방위로 불만을 쏟아냈다.\n  그는 우선 \"독일에 5만2000명의 병사를 주둔하는 데 이는 엄청난 규모이며 미국에 막대한 비용\"이라며 \"독일은 북대서양조약기구(나토)에 아주 많은 체납을 하고 있다\"고 말했다.\n  \"독일은 국내총생산(GDP)의 2%를 방위비를 내기로 돼 있지만 1%밖에 지불하지 않는다.\n  그들은 수십억 달러를 체납하고 있다\"라고도 했다.\n  그러면서 \"그래서 주독 미군 숫자를 2만5000명으로 줄이고 있다.\n  무슨 일이 일어날지 두고 보자\"라고도 덧붙였다.\n  앞서 월스트리트저널이 지난 5일 트럼프 대통령이 국방부에 현역 병력 기준 3만4500명인 주독미군에서 9500명을 철수시키라고 지시하는 각서에 서명했다고 보도한 지 열흘 만에 직접 확인한 셈이다.\n   트럼프 대통령은 \"모든 사람이 (주독미군 감축 결정에 관해) 나와 러시아의 관계를 얘기하지만, 나는 이 문제를 오래전에 꺼냈다\"며 \"왜 독일은 러시아에 에너지 구매로 수십억 달러를 지불하는 데 우리가 독일을 지켜줘야 하나.\n  이런 식은 통하지 않는다\"라고 말했다.\n  독일의 러시아 가스도입 사업인 노드 스트림 2를 거론한 셈이다.\n  그러면서 \"우리가 독일을 지켜주는데 그들은 방위비를 연체하고 있다\"며 \"이건 말이 안 된다\"라고 거듭 말했다.\n  그는 또 \"상황에 따라 다르지만, 우리는 독일에 5만2000명을 주둔하고 그들은 봉급을 많이 받는 병사들\"이라며 \"막대한 금액을 현지에서 쓰기 때문에 주둔기지 주변은 아주 번창하고 독일이 이득을 가져가고 있다\"고 상세하게 설명했다.\n   트럼프 대통령은 \"이 외에 독일은 무역에 관해서도 우리를 몹시 나쁘게 대우한다.\n  독일이 최대 회원국인 유럽연합(EU)과 무역협상 중이지만 현재 그들과 협상에 만족스럽지 않다\"라고도 했다.\n ",
		"passage_Cnt": 1216
	},
	"Annotation": {
		"summary1": "트럼프 미국 대통령은 독일이 GDP의 2% 방위비를 낼 때까지 주독 미군 규모를 절반으로 줄일 것이라고 밝혔다.",
		"summary2": "도널드 트럼프 미국 대통령이 15일(현지시간) \"독일이 국내총생산(GDP)의 2% 방위비를 낼 때까지 미군을 절반 규모로 감축할 것\"이라고 밝혔다. 주독 미군 규모를 최대 5만2000명에서 2만5000명으로 줄이겠다고 하면서다.",
		"summary3": null,
		"summary_3_cnt": null
	}
}